HardwareProvider/__init__.py
HardwareProvider-0.1.7.dist-info/LICENSE
HardwareProvider-0.1.7.dist-info/METADATA
HardwareProvider-0.1.7.dist-info/WHEEL
HardwareProvider-0.1.7.dist-info/top_level.txt
HardwareProvider-0.1.7.dist-info/RECORD
